oomllama/__init__.py
oomllama/_oomllama.cpython-313-x86_64-linux-gnu.so
oomllama-0.2.0.dist-info/METADATA
oomllama-0.2.0.dist-info/WHEEL
oomllama-0.2.0.dist-info/entry_points.txt
oomllama-0.2.0.dist-info/RECORD
