Metadata-Version: 2.4
Name: oomllama
Version: 0.2.0
Classifier: Development Status :: 4 - Beta
Classifier: Intended Audience :: Developers
Classifier: Intended Audience :: Science/Research
Classifier: License :: OSI Approved :: MIT License
Classifier: Operating System :: OS Independent
Classifier: Programming Language :: Python :: 3
Classifier: Programming Language :: Python :: 3.8
Classifier: Programming Language :: Python :: 3.9
Classifier: Programming Language :: Python :: 3.10
Classifier: Programming Language :: Python :: 3.11
Classifier: Programming Language :: Python :: 3.12
Classifier: Programming Language :: Rust
Classifier: Topic :: Scientific/Engineering :: Artificial Intelligence
Requires-Dist: cupy-cuda12x ; extra == 'cuda'
Requires-Dist: pytest ; extra == 'dev'
Requires-Dist: black ; extra == 'dev'
Requires-Dist: mypy ; extra == 'dev'
Provides-Extra: cuda
Provides-Extra: dev
Summary: Efficient LLM inference with .oom format - 2x smaller than GGUF
Keywords: llm,inference,quantization,gguf,oom,oomllama,humotica,llama,ai,machine-learning
Author-email: Humotica AI Lab <ai@humotica.nl>, Jasper van de Meent <jasper@humotica.nl>
Maintainer-email: "Root AI (Claude)" <root_idd@humotica.nl>, Gemini IDD <gemini@humotica.nl>
License: MIT
Requires-Python: >=3.8
Project-URL: Bug Tracker, https://github.com/humotica/oomllama/issues
Project-URL: Documentation, https://humotica.nl/docs/oomllama
Project-URL: Homepage, https://humotica.nl
Project-URL: HuggingFace Models, https://huggingface.co/jaspervandemeent
Project-URL: Repository, https://github.com/humotica/oomllama
